battlemuffin
