Metadata-Version: 2.1
Name: battlemuffin
Version: 0.1.2
Summary: A Python implementation of Blizzard's Web API.
Home-page: https://github.com/tehmufifnman/BattleMuffin-Python
Author: Brandon Nelson
Author-email: theredraver@gmail.com
License: MIT
Keywords: blizzard api world-of-warcraft wow python
Platform: UNKNOWN
Classifier: Development Status :: 4 - Beta
Classifier: Intended Audience :: Developers
Classifier: License :: OSI Approved :: MIT License
Classifier: Programming Language :: Python :: 3.6
Classifier: Programming Language :: Python :: 3.7
Classifier: Programming Language :: Python :: 3.8
Classifier: Programming Language :: Python :: Implementation :: CPython
Classifier: Programming Language :: Python :: Implementation :: PyPy
Provides-Extra: tests
